rattata/__init__.py
rattata/converters.py
rattata/errors.py
rattata/type_mappings.py
rattata-0.1.0.dist-info/LICENSE
rattata-0.1.0.dist-info/METADATA
rattata-0.1.0.dist-info/WHEEL
rattata-0.1.0.dist-info/top_level.txt
rattata-0.1.0.dist-info/RECORD
