Metadata-Version: 2.1
Name: rattata
Version: 0.1.0
Summary: Convert between Polars schemas and Python data structures (dataclasses, TypedDicts, namedtuples)
Author-email: Odos Matthews <odosmatthews@gmail.com>
License: MIT
Keywords: polars,dataclass,typeddict,namedtuple,schema,conversion
Classifier: Development Status :: 3 - Alpha
Classifier: Intended Audience :: Developers
Classifier: License :: OSI Approved :: MIT License
Classifier: Programming Language :: Python :: 3
Classifier: Programming Language :: Python :: 3.8
Classifier: Programming Language :: Python :: 3.9
Classifier: Programming Language :: Python :: 3.10
Classifier: Programming Language :: Python :: 3.11
Classifier: Programming Language :: Python :: 3.12
Classifier: Topic :: Software Development :: Libraries :: Python Modules
Requires-Python: >=3.8
License-File: LICENSE
Requires-Dist: polars>=0.19.0
Requires-Dist: typing-extensions>=4.0.0; python_version < "3.9"
Provides-Extra: dev
Requires-Dist: pytest>=7.0.0; extra == "dev"
Requires-Dist: pytest-cov>=4.0.0; extra == "dev"
Requires-Dist: black>=23.0.0; extra == "dev"
Requires-Dist: ruff>=0.1.0; extra == "dev"
